pfs/api/v1/api_pb2.py
pfs/api/v1/api_pb2.pyi
pfs/api/v1/api_pb2_grpc.py
pfs/api/v1/derive_pb2.py
pfs/api/v1/derive_pb2.pyi
pfs/api/v1/derive_pb2_grpc.py
pfs/api/v1/job_pb2.py
pfs/api/v1/job_pb2.pyi
pfs/api/v1/job_pb2_grpc.py
pfs/api/v1/model_pb2.py
pfs/api/v1/model_pb2.pyi
pfs/api/v1/model_pb2_grpc.py
pfs/api/v1/source_connection_pb2.py
pfs/api/v1/source_connection_pb2.pyi
pfs/api/v1/source_connection_pb2_grpc.py
pfs/api/v1/store_pb2.py
pfs/api/v1/store_pb2.pyi
pfs/api/v1/store_pb2_grpc.py
pfs_api-0.1.0.dist-info/WHEEL
pfs_api-0.1.0.dist-info/METADATA
pfs_api-0.1.0.dist-info/RECORD
